build/lib/containers/airflow/health_check.py
build/lib/legion-cicd/tools/tests.py
build/lib/legion-cicd/tools/update_version_files.py
build/lib/odahuflow/airflow_plugin/__init__.py
build/lib/odahuflow/airflow_plugin/__version__.py
build/lib/odahuflow/airflow_plugin/api.py
build/lib/odahuflow/airflow_plugin/batch.py
build/lib/odahuflow/airflow_plugin/connection.py
build/lib/odahuflow/airflow_plugin/deployment.py
build/lib/odahuflow/airflow_plugin/model.py
build/lib/odahuflow/airflow_plugin/packaging.py
build/lib/odahuflow/airflow_plugin/plugin.py
build/lib/odahuflow/airflow_plugin/resources.py
build/lib/odahuflow/airflow_plugin/training.py
build/lib/tests/__init__.py
build/lib/tests/test_simple_dag.py
containers/airflow/health_check.py
legion-cicd/tools/tests.py
legion-cicd/tools/update_version_files.py
odahu_flow_airflow_plugin-1.6.0.data/data/README.md
odahuflow/airflow_plugin/__init__.py
odahuflow/airflow_plugin/__version__.py
odahuflow/airflow_plugin/api.py
odahuflow/airflow_plugin/batch.py
odahuflow/airflow_plugin/connection.py
odahuflow/airflow_plugin/deployment.py
odahuflow/airflow_plugin/model.py
odahuflow/airflow_plugin/packaging.py
odahuflow/airflow_plugin/plugin.py
odahuflow/airflow_plugin/resources.py
odahuflow/airflow_plugin/training.py
tests/__init__.py
tests/test_simple_dag.py
odahu_flow_airflow_plugin-1.6.0.dist-info/LICENSE
odahu_flow_airflow_plugin-1.6.0.dist-info/METADATA
odahu_flow_airflow_plugin-1.6.0.dist-info/WHEEL
odahu_flow_airflow_plugin-1.6.0.dist-info/entry_points.txt
odahu_flow_airflow_plugin-1.6.0.dist-info/top_level.txt
odahu_flow_airflow_plugin-1.6.0.dist-info/RECORD
