Metadata-Version: 2.1
Name: odahu-flow-airflow-plugin
Version: 1.6.0
Summary: UNKNOWN
Home-page: UNKNOWN
Author: Vlad Tokarev, Vitalik Solodilov
Author-email: vlad.tokarev.94@gmail.com, mcdkr@yandex.ru
License: Apache v2
Keywords: airflow odahuflow
Platform: UNKNOWN
Classifier: Programming Language :: Python :: 3.6
Classifier: Programming Language :: Python :: 3.7
Requires-Python: >=3.6
License-File: LICENSE
Requires-Dist: odahu-flow-sdk (==1.5.0rc5)
Requires-Dist: requests (>=2.22.0)
Provides-Extra: testing
Requires-Dist: pytest (>=5.1.2) ; extra == 'testing'
Requires-Dist: pytest-mock (>=1.10.4) ; extra == 'testing'
Requires-Dist: pytest-cov (>=2.7.1) ; extra == 'testing'
Requires-Dist: pylint (>=2.3.0) ; extra == 'testing'
Requires-Dist: apache-airflow (==1.10.14) ; extra == 'testing'
Requires-Dist: google-api-python-client ; extra == 'testing'
